#define OPCODE_NOP	0 
#define OPCODE_ACONST_NULL	1 
#define OPCODE_ICONST_M1	2 
#define OPCODE_ICONST_0	3 
#define OPCODE_ICONST_1	4 
#define OPCODE_ICONST_2	5 
#define OPCODE_ICONST_3	6 
#define OPCODE_ICONST_4	7 
#define OPCODE_ICONST_5	8 
#define OPCODE_LCONST_0	9 
#define OPCODE_LCONST_1	10 
#define OPCODE_FCONST_0	11 
#define OPCODE_FCONST_1	12 
#define OPCODE_FCONST_2	13 
#define OPCODE_DCONST_0	14 
#define OPCODE_DCONST_1	15 
#define OPCODE_BIPUSH	16 
#define OPCODE_SIPUSH	17 
#define OPCODE_LDC	18 
#define OPCODE_LDC_W	19 
#define OPCODE_LDC2_W	20 
#define OPCODE_ILOAD	21 
#define OPCODE_LLOAD	22 
#define OPCODE_FLOAD	23 
#define OPCODE_DLOAD	24 
#define OPCODE_ALOAD	25 
#define OPCODE_ILOAD_0	26 
#define OPCODE_ILOAD_1	27 
#define OPCODE_ILOAD_2	28 
#define OPCODE_ILOAD_3	29 
#define OPCODE_LLOAD_0	30 
#define OPCODE_LLOAD_1	31 
#define OPCODE_LLOAD_2	32 
#define OPCODE_LLOAD_3	33 
#define OPCODE_FLOAD_0	34 
#define OPCODE_FLOAD_1	35 
#define OPCODE_FLOAD_2	36 
#define OPCODE_FLOAD_3	37 
#define OPCODE_DLOAD_0	38 
#define OPCODE_DLOAD_1	39 
#define OPCODE_DLOAD_2	40 
#define OPCODE_DLOAD_3	41 
#define OPCODE_ALOAD_0	42 
#define OPCODE_ALOAD_1	43 
#define OPCODE_ALOAD_2	44 
#define OPCODE_ALOAD_3	45 
#define OPCODE_IALOAD	46 
#define OPCODE_LALOAD   47
#define OPCODE_FALOAD	48 
#define OPCODE_DALOAD   49
#define OPCODE_AALOAD	50 
#define OPCODE_BALOAD	51 
#define OPCODE_CALOAD	52 
#define OPCODE_SALOAD   53
#define OPCODE_ISTORE	54 
#define OPCODE_LSTORE	55 
#define OPCODE_FSTORE	56 
#define OPCODE_DSTORE	57 
#define OPCODE_ASTORE	58 
#define OPCODE_ISTORE_0	59 
#define OPCODE_ISTORE_1	60 
#define OPCODE_ISTORE_2	61 
#define OPCODE_ISTORE_3	62 
#define OPCODE_LSTORE_0	63 
#define OPCODE_LSTORE_1	64 
#define OPCODE_LSTORE_2	65 
#define OPCODE_LSTORE_3	66 
#define OPCODE_FSTORE_0	67 
#define OPCODE_FSTORE_1	68 
#define OPCODE_FSTORE_2	69 
#define OPCODE_FSTORE_3	70 
#define OPCODE_DSTORE_0	71 
#define OPCODE_DSTORE_1	72 
#define OPCODE_DSTORE_2	73 
#define OPCODE_DSTORE_3	74 
#define OPCODE_ASTORE_0	75 
#define OPCODE_ASTORE_1	76 
#define OPCODE_ASTORE_2	77 
#define OPCODE_ASTORE_3	78 
#define OPCODE_IASTORE	79 
#define OPCODE_LASTORE	80 
#define OPCODE_FASTORE	81 
#define OPCODE_DASTORE	82 
#define OPCODE_AASTORE	83 
#define OPCODE_BASTORE	84 
#define OPCODE_CASTORE	85 
#define OPCODE_POP	87 
#define OPCODE_POP2	88 
#define OPCODE_DUP	89 
#define OPCODE_DUP_X1	90 
#define OPCODE_DUP_X2	91 
#define OPCODE_DUP2	92 
#define OPCODE_DUP2_X1	93 
#define OPCODE_DUP2_X2	94 
#define OPCODE_SWAP	95 
#define OPCODE_IADD	96 
#define OPCODE_LADD	97 
#define OPCODE_FADD	98 
#define OPCODE_DADD	99 
#define OPCODE_ISUB	100 
#define OPCODE_LSUB	101 
#define OPCODE_FSUB	102 
#define OPCODE_DSUB	103 
#define OPCODE_IMUL	104 
#define OPCODE_LMUL	105 
#define OPCODE_FMUL	106 
#define OPCODE_DMUL	107 
#define OPCODE_IDIV	108 
#define OPCODE_LDIV	109 
#define OPCODE_FDIV	110 
#define OPCODE_DDIV	111 
#define OPCODE_IREM	112 
#define OPCODE_LREM	113 
#define OPCODE_FREM	114 
#define OPCODE_DREM	115 
#define OPCODE_INEG	116 
#define OPCODE_LNEG	117 
#define OPCODE_FNEG	118 
#define OPCODE_DNEG	119 
#define OPCODE_ISHL	120 
#define OPCODE_LSHL	121 
#define OPCODE_ISHR	122 
#define OPCODE_LSHR	123 
#define OPCODE_IUSHR	124 
#define OPCODE_LUSHR	125 
#define OPCODE_IAND	126 
#define OPCODE_LAND	127 
#define OPCODE_IOR	128 
#define OPCODE_LOR	129 
#define OPCODE_IXOR	130 
#define OPCODE_LXOR	131 
#define OPCODE_IINC	132 
#define OPCODE_I2L	133 
#define OPCODE_I2F	134 
#define OPCODE_I2D	135 
#define OPCODE_L2I	136 
#define OPCODE_L2F	137 
#define OPCODE_L2D	138 
#define OPCODE_F2I	139 
#define OPCODE_F2L	140 
#define OPCODE_F2D	141 
#define OPCODE_D2I	142 
#define OPCODE_D2L	143 
#define OPCODE_D2F	144 
#define OPCODE_I2B	145 
#define OPCODE_I2C	146 
#define OPCODE_I2S	147 
#define OPCODE_LCMP	148 
#define OPCODE_FCMPL	149 
#define OPCODE_FCMPG	150 
#define OPCODE_DCMPL	151 
#define OPCODE_DCMPG	152 
#define OPCODE_IFEQ	153 
#define OPCODE_IFNE	154 
#define OPCODE_IFLT	155 
#define OPCODE_IFGE	156 
#define OPCODE_IFGT	157 
#define OPCODE_IFLE	158 
#define OPCODE_IF_ICMPEQ	159 
#define OPCODE_IF_ICMPNE	160 
#define OPCODE_IF_ICMPLT	161 
#define OPCODE_IF_ICMPGE	162 
#define OPCODE_IF_ICMPGT	163 
#define OPCODE_IF_ICMPLE	164 
#define OPCODE_IF_ACMPEQ	165 
#define OPCODE_IF_ACMPNE	166 
#define OPCODE_GOTO	167 
#define OPCODE_JSR	168 
#define OPCODE_RET	169 
#define OPCODE_TABLESWITCH	170 
#define OPCODE_LOOKUPSWITCH	171 
#define OPCODE_IRETURN	172 
#define OPCODE_LRETURN	173 
#define OPCODE_FRETURN	174 
#define OPCODE_DRETURN	175 
#define OPCODE_ARETURN	176 
#define OPCODE_RETURN	177 
#define OPCODE_GETSTATIC	178 
#define OPCODE_PUTSTATIC	179 
#define OPCODE_GETFIELD	180 
#define OPCODE_PUTFIELD	181 
#define OPCODE_INVOKEINTERFACE	185 
#define OPCODE_NEW	187 
#define OPCODE_ANEWARRAY	189 
#define OPCODE_ARRAYLENGTH	190 
#define OPCODE_ATHROW	191 
#define OPCODE_CHECKCAST	192 
#define OPCODE_INSTANCEOF	193 
#define OPCODE_MONITORENTER	194 
#define OPCODE_MONITOREXIT	195 
#define OPCODE_WIDE	196 
#define OPCODE_MULTIANEWARRAY	197 
#define OPCODE_IFNULL	198 
#define OPCODE_IFNONNULL	199 
#define OPCODE_GOTO_W	200 
#define OPCODE_JSR_W	201 
#define OPCODE_GETFIELD_QUICK	206 
#define OPCODE_PUTFIELD_QUICK	207 
#define OPCODE_GETFIELD2_QUICK	208 
#define OPCODE_PUTFIELD2_QUICK	209 
#define OPCODE_INVOKEVIRTUAL_QUICK	214 
#define OPCODE_INVOKENONVIRTUAL_QUICK	215 
#define OPCODE_DEBUG_PRINT	221 
#define OPCODE_PRINT_STRING	223 
#define OPCODE_WIDE_ILOAD	277 
#define OPCODE_WIDE_LLOAD	278 
#define OPCODE_WIDE_FLOAD	279 
#define OPCODE_WIDE_DLOAD	280 
#define OPCODE_WIDE_ALOAD	281 
#define OPCODE_WIDE_ISTORE	310 
#define OPCODE_WIDE_LSTORE	311 
#define OPCODE_WIDE_FSTORE	312 
#define OPCODE_WIDE_DSTORE	313 
#define OPCODE_WIDE_ASTORE	314 
#define OPCODE_WIDE_IINC	388 
#define OPCODE_WIDE_RET	425 
case OPCODE_NOP: {
INCPC(1);
NEXT_INSTRUCTION;
}
case OPCODE_ACONST_NULL: {
INCPC(1);
NEXT_INSTRUCTION;
}
case OPCODE_ICONST_M1: {
INCPC(1);
NEXT_INSTRUCTION;
}
case OPCODE_ICONST_0: {
INCPC(1);
NEXT_INSTRUCTION;
}
case OPCODE_ICONST_1: {
INCPC(1);
NEXT_INSTRUCTION;
}
case OPCODE_ICONST_2: {
INCPC(1);
NEXT_INSTRUCTION;
}
case OPCODE_ICONST_3: {
INCPC(1);
NEXT_INSTRUCTION;
}
case OPCODE_ICONST_4: {
INCPC(1);
NEXT_INSTRUCTION;
}
case OPCODE_ICONST_5: {
INCPC(1);
NEXT_INSTRUCTION;
}
case OPCODE_LCONST_0: {
INCPC(1);
NEXT_INSTRUCTION;
}
case OPCODE_LCONST_1: {
INCPC(1);
NEXT_INSTRUCTION;
}
case OPCODE_FCONST_0: {
INCPC(1);
NEXT_INSTRUCTION;
}
case OPCODE_FCONST_1: {
INCPC(1);
NEXT_INSTRUCTION;
}
case OPCODE_FCONST_2: {
INCPC(1);
NEXT_INSTRUCTION;
}
case OPCODE_DCONST_0: {
INCPC(1);
NEXT_INSTRUCTION;
}
case OPCODE_DCONST_1: {
INCPC(1);
NEXT_INSTRUCTION;
}
case OPCODE_BIPUSH: {
INCPC(2);
NEXT_INSTRUCTION;
}
case OPCODE_SIPUSH: {
INCPC(3);
NEXT_INSTRUCTION;
}
case OPCODE_LDC: {
INCPC(2);
NEXT_INSTRUCTION;
}
case OPCODE_LDC_W: {
INCPC(3);
NEXT_INSTRUCTION;
}
case OPCODE_LDC2_W: {
INCPC(3);
NEXT_INSTRUCTION;
}
case OPCODE_ILOAD: {
INCPC(2);
NEXT_INSTRUCTION;
}
case OPCODE_LLOAD: {
INCPC(2);
NEXT_INSTRUCTION;
}
case OPCODE_FLOAD: {
INCPC(2);
NEXT_INSTRUCTION;
}
case OPCODE_DLOAD: {
INCPC(2);
NEXT_INSTRUCTION;
}
case OPCODE_ALOAD: {
INCPC(2);
NEXT_INSTRUCTION;
}
case OPCODE_ILOAD_0: {
INCPC(1);
NEXT_INSTRUCTION;
}
case OPCODE_ILOAD_1: {
INCPC(1);
NEXT_INSTRUCTION;
}
case OPCODE_ILOAD_2: {
INCPC(1);
NEXT_INSTRUCTION;
}
case OPCODE_ILOAD_3: {
INCPC(1);
NEXT_INSTRUCTION;
}
case OPCODE_LLOAD_0: {
INCPC(1);
NEXT_INSTRUCTION;
}
case OPCODE_LLOAD_1: {
INCPC(1);
NEXT_INSTRUCTION;
}
case OPCODE_LLOAD_2: {
INCPC(1);
NEXT_INSTRUCTION;
}
case OPCODE_LLOAD_3: {
INCPC(1);
NEXT_INSTRUCTION;
}
case OPCODE_FLOAD_0: {
INCPC(1);
NEXT_INSTRUCTION;
}
case OPCODE_FLOAD_1: {
INCPC(1);
NEXT_INSTRUCTION;
}
case OPCODE_FLOAD_2: {
INCPC(1);
NEXT_INSTRUCTION;
}
case OPCODE_FLOAD_3: {
INCPC(1);
NEXT_INSTRUCTION;
}
case OPCODE_DLOAD_0: {
INCPC(1);
NEXT_INSTRUCTION;
}
case OPCODE_DLOAD_1: {
INCPC(1);
NEXT_INSTRUCTION;
}
case OPCODE_DLOAD_2: {
INCPC(1);
NEXT_INSTRUCTION;
}
case OPCODE_DLOAD_3: {
INCPC(1);
NEXT_INSTRUCTION;
}
case OPCODE_ALOAD_0: {
INCPC(1);
NEXT_INSTRUCTION;
}
case OPCODE_ALOAD_1: {
INCPC(1);
NEXT_INSTRUCTION;
}
case OPCODE_ALOAD_2: {
INCPC(1);
NEXT_INSTRUCTION;
}
case OPCODE_ALOAD_3: {
INCPC(1);
NEXT_INSTRUCTION;
}
case OPCODE_IALOAD: {
INCPC(1);
NEXT_INSTRUCTION;
}
case OPCODE_DALOAD: {
INCPC(1);
NEXT_INSTRUCTION;
}
case OPCODE_LALOAD: {
INCPC(1);
NEXT_INSTRUCTION;
}
case OPCODE_FALOAD: {
INCPC(1);
NEXT_INSTRUCTION;
}
case OPCODE_AALOAD: {
{
}
INCPC(1);
NEXT_INSTRUCTION;
}
case OPCODE_BALOAD: {
INCPC(1);
NEXT_INSTRUCTION;
}
case OPCODE_CALOAD: {
INCPC(1);
NEXT_INSTRUCTION;
}
case OPCODE_SALOAD: {
INCPC(1);
NEXT_INSTRUCTION;
}
case OPCODE_ISTORE: {
INCPC(2);
NEXT_INSTRUCTION;
}
case OPCODE_LSTORE: {
INCPC(2);
NEXT_INSTRUCTION;
}
case OPCODE_FSTORE: {
INCPC(2);
NEXT_INSTRUCTION;
}
case OPCODE_DSTORE: {
INCPC(2);
NEXT_INSTRUCTION;
}
case OPCODE_ASTORE: {
INCPC(2);
NEXT_INSTRUCTION;
}
case OPCODE_ISTORE_0: {
INCPC(1);
NEXT_INSTRUCTION;
}
case OPCODE_ISTORE_1: {
INCPC(1);
NEXT_INSTRUCTION;
}
case OPCODE_ISTORE_2: {
INCPC(1);
NEXT_INSTRUCTION;
}
case OPCODE_ISTORE_3: {
INCPC(1);
NEXT_INSTRUCTION;
}
case OPCODE_LSTORE_0: {
INCPC(1);
NEXT_INSTRUCTION;
}
case OPCODE_LSTORE_1: {
INCPC(1);
NEXT_INSTRUCTION;
}
case OPCODE_LSTORE_2: {
INCPC(1);
NEXT_INSTRUCTION;
}
case OPCODE_LSTORE_3: {
INCPC(1);
NEXT_INSTRUCTION;
}
case OPCODE_FSTORE_0: {
INCPC(1);
NEXT_INSTRUCTION;
}
case OPCODE_FSTORE_1: {
INCPC(1);
NEXT_INSTRUCTION;
}
case OPCODE_FSTORE_2: {
INCPC(1);
NEXT_INSTRUCTION;
}
case OPCODE_FSTORE_3: {
INCPC(1);
NEXT_INSTRUCTION;
}
case OPCODE_DSTORE_0: {
INCPC(1);
NEXT_INSTRUCTION;
}
case OPCODE_DSTORE_1: {
INCPC(1);
NEXT_INSTRUCTION;
}
case OPCODE_DSTORE_2: {
INCPC(1);
NEXT_INSTRUCTION;
}
case OPCODE_DSTORE_3: {
INCPC(1);
NEXT_INSTRUCTION;
}
case OPCODE_ASTORE_0: {
INCPC(1);
NEXT_INSTRUCTION;
}
case OPCODE_ASTORE_1: {
INCPC(1);
NEXT_INSTRUCTION;
}
case OPCODE_ASTORE_2: {
INCPC(1);
NEXT_INSTRUCTION;
}
case OPCODE_ASTORE_3: {
INCPC(1);
NEXT_INSTRUCTION;
}
case OPCODE_IASTORE: {
INCPC(1);
NEXT_INSTRUCTION;
}
case OPCODE_LASTORE: {
INCPC(1);
NEXT_INSTRUCTION;
}
case OPCODE_FASTORE: {
INCPC(1);
NEXT_INSTRUCTION;
}
case OPCODE_DASTORE: {
INCPC(1);
NEXT_INSTRUCTION;
}
case OPCODE_AASTORE: {
INCPC(1);
NEXT_INSTRUCTION;
}
case OPCODE_BASTORE: {
INCPC(1);
NEXT_INSTRUCTION;
}
case OPCODE_CASTORE: {
INCPC(1);
NEXT_INSTRUCTION;
}
case OPCODE_POP: {
INCPC(1);
NEXT_INSTRUCTION;
}
case OPCODE_POP2: {
INCPC(1);
NEXT_INSTRUCTION;
}
case OPCODE_DUP: {
INCPC(1);
NEXT_INSTRUCTION;
}
case OPCODE_DUP_X1: {
INCPC(1);
NEXT_INSTRUCTION;
}
case OPCODE_DUP_X2: {
INCPC(1);
NEXT_INSTRUCTION;
}
case OPCODE_DUP2: {
INCPC(1);
NEXT_INSTRUCTION;
}
case OPCODE_DUP2_X1: {
INCPC(1);
NEXT_INSTRUCTION;
}
case OPCODE_DUP2_X2: {
INCPC(1);
NEXT_INSTRUCTION;
}
case OPCODE_SWAP: {
INCPC(1);
NEXT_INSTRUCTION;
}
case OPCODE_IADD: {
INCPC(1);
NEXT_INSTRUCTION;
}
case OPCODE_LADD: {
INCPC(1);
NEXT_INSTRUCTION;
}
case OPCODE_FADD: {
INCPC(1);
NEXT_INSTRUCTION;
}
case OPCODE_DADD: {
INCPC(1);
NEXT_INSTRUCTION;
}
case OPCODE_ISUB: {
INCPC(1);
NEXT_INSTRUCTION;
}
case OPCODE_LSUB: {
INCPC(1);
NEXT_INSTRUCTION;
}
case OPCODE_FSUB: {
INCPC(1);
NEXT_INSTRUCTION;
}
case OPCODE_DSUB: {
INCPC(1);
NEXT_INSTRUCTION;
}
case OPCODE_IMUL: {
INCPC(1);
NEXT_INSTRUCTION;
}
case OPCODE_LMUL: {
INCPC(1);
NEXT_INSTRUCTION;
}
case OPCODE_FMUL: {
INCPC(1);
NEXT_INSTRUCTION;
}
case OPCODE_DMUL: {
INCPC(1);
NEXT_INSTRUCTION;
}
case OPCODE_IDIV: {
INCPC(1);
NEXT_INSTRUCTION;
}
case OPCODE_LDIV: {
INCPC(1);
NEXT_INSTRUCTION;
}
case OPCODE_FDIV: {
INCPC(1);
NEXT_INSTRUCTION;
}
case OPCODE_DDIV: {
INCPC(1);
NEXT_INSTRUCTION;
}
case OPCODE_IREM: {
INCPC(1);
NEXT_INSTRUCTION;
}
case OPCODE_LREM: {
INCPC(1);
NEXT_INSTRUCTION;
}
case OPCODE_FREM: {
INCPC(1);
NEXT_INSTRUCTION;
}
case OPCODE_DREM: {
INCPC(1);
NEXT_INSTRUCTION;
}
case OPCODE_INEG: {
INCPC(1);
NEXT_INSTRUCTION;
}
case OPCODE_LNEG: {
INCPC(1);
NEXT_INSTRUCTION;
}
case OPCODE_FNEG: {
INCPC(1);
NEXT_INSTRUCTION;
}
case OPCODE_DNEG: {
INCPC(1);
NEXT_INSTRUCTION;
}
case OPCODE_ISHL: {
INCPC(1);
NEXT_INSTRUCTION;
}
case OPCODE_LSHL: {
INCPC(1);
NEXT_INSTRUCTION;
}
case OPCODE_ISHR: {
INCPC(1);
NEXT_INSTRUCTION;
}
case OPCODE_LSHR: {
INCPC(1);
NEXT_INSTRUCTION;
}
case OPCODE_IUSHR: {
INCPC(1);
NEXT_INSTRUCTION;
}
case OPCODE_LUSHR: {
INCPC(1);
NEXT_INSTRUCTION;
}
case OPCODE_IAND: {
INCPC(1);
NEXT_INSTRUCTION;
}
case OPCODE_LAND: {
INCPC(1);
NEXT_INSTRUCTION;
}
case OPCODE_IOR: {
INCPC(1);
NEXT_INSTRUCTION;
}
case OPCODE_LOR: {
INCPC(1);
NEXT_INSTRUCTION;
}
case OPCODE_IXOR: {
INCPC(1);
NEXT_INSTRUCTION;
}
case OPCODE_LXOR: {
INCPC(1);
NEXT_INSTRUCTION;
}
case OPCODE_IINC: {
INCPC(3);
NEXT_INSTRUCTION;
}
case OPCODE_I2L: {
INCPC(1);
NEXT_INSTRUCTION;
}
case OPCODE_I2F: {
INCPC(1);
NEXT_INSTRUCTION;
}
case OPCODE_I2D: {
INCPC(1);
NEXT_INSTRUCTION;
}
case OPCODE_L2I: {
INCPC(1);
NEXT_INSTRUCTION;
}
case OPCODE_L2F: {
INCPC(1);
NEXT_INSTRUCTION;
}
case OPCODE_L2D: {
INCPC(1);
NEXT_INSTRUCTION;
}
case OPCODE_F2I: {
INCPC(1);
NEXT_INSTRUCTION;
}
case OPCODE_F2L: {
INCPC(1);
NEXT_INSTRUCTION;
}
case OPCODE_F2D: {
INCPC(1);
NEXT_INSTRUCTION;
}
case OPCODE_D2I: {
INCPC(1);
NEXT_INSTRUCTION;
}
case OPCODE_D2L: {
INCPC(1);
NEXT_INSTRUCTION;
}
case OPCODE_D2F: {
INCPC(1);
NEXT_INSTRUCTION;
}
case OPCODE_I2B: {
INCPC(1);
NEXT_INSTRUCTION;
}
case OPCODE_I2C: {
INCPC(1);
NEXT_INSTRUCTION;
}
case OPCODE_I2S: {
INCPC(1);
NEXT_INSTRUCTION;
}
case OPCODE_LCMP: {
INCPC(1);
NEXT_INSTRUCTION;
}
case OPCODE_FCMPL: {
INCPC(1);
NEXT_INSTRUCTION;
}
case OPCODE_FCMPG: {
INCPC(1);
NEXT_INSTRUCTION;
}
case OPCODE_DCMPL: {
INCPC(1);
NEXT_INSTRUCTION;
}
case OPCODE_DCMPG: {
INCPC(1);
NEXT_INSTRUCTION;
}
case OPCODE_IFEQ: {
INCPC(3);
NEXT_INSTRUCTION_WITH_POLL_CHECK;
}
case OPCODE_IFNE: {
INCPC(3);
NEXT_INSTRUCTION_WITH_POLL_CHECK;
}
case OPCODE_IFLT: {
INCPC(3);
NEXT_INSTRUCTION_WITH_POLL_CHECK;
}
case INVOKE_SYSTEM: {
INCPC(3);
NEXT_INSTRUCTION_WITH_POLL_CHECK;
}
case OPCODE_IFGE: {
INCPC(3);
NEXT_INSTRUCTION_WITH_POLL_CHECK;
}
case OPCODE_IFGT: {
INCPC(3);
NEXT_INSTRUCTION_WITH_POLL_CHECK;
}
case OPCODE_IFLE: {
INCPC(3);
NEXT_INSTRUCTION_WITH_POLL_CHECK;
}
case OPCODE_IF_ICMPEQ: {
INCPC(3);
NEXT_INSTRUCTION_WITH_POLL_CHECK;
}
case OPCODE_IF_ICMPNE: {
INCPC(3);
NEXT_INSTRUCTION_WITH_POLL_CHECK;
}
case OPCODE_IF_ICMPLT: {
INCPC(3);
NEXT_INSTRUCTION_WITH_POLL_CHECK;
}
case OPCODE_IF_ICMPGE: {
INCPC(3);
NEXT_INSTRUCTION_WITH_POLL_CHECK;
}
case OPCODE_IF_ICMPGT: {
INCPC(3);
NEXT_INSTRUCTION_WITH_POLL_CHECK;
}
case OPCODE_IF_ICMPLE: {
INCPC(3);
NEXT_INSTRUCTION_WITH_POLL_CHECK;
}
case OPCODE_IF_ACMPEQ: {
INCPC(3);
NEXT_INSTRUCTION_WITH_POLL_CHECK;
}
case OPCODE_IF_ACMPNE: {
INCPC(3);
NEXT_INSTRUCTION_WITH_POLL_CHECK;
}
case OPCODE_GOTO: {
INCPC(1);
NEXT_INSTRUCTION_WITH_POLL_CHECK;
}
case OPCODE_JSR: {
NEXT_INSTRUCTION_WITH_POLL_CHECK;
}
case OPCODE_RET: {
NEXT_INSTRUCTION_WITH_POLL_CHECK;
}
case OPCODE_TABLESWITCH: {
NEXT_INSTRUCTION_WITH_POLL_CHECK;
}
case OPCODE_LOOKUPSWITCH: {
NEXT_INSTRUCTION_WITH_POLL_CHECK;
}
case OPCODE_IRETURN: {
NEXT_INSTRUCTION_WITH_POLL_CHECK;
}
case OPCODE_LRETURN: {
NEXT_INSTRUCTION_WITH_POLL_CHECK;
}
case OPCODE_FRETURN: {
NEXT_INSTRUCTION_WITH_POLL_CHECK;
}
case OPCODE_DRETURN: {
NEXT_INSTRUCTION_WITH_POLL_CHECK;
}
case OPCODE_ARETURN: {
NEXT_INSTRUCTION_WITH_POLL_CHECK;
}
case OPCODE_RETURN: {
NEXT_INSTRUCTION_WITH_POLL_CHECK;
}
case OPCODE_GETSTATIC: {
INCPC(3);
NEXT_INSTRUCTION;
}
case OPCODE_PUTSTATIC: {
INCPC(3);
NEXT_INSTRUCTION;
}
case OPCODE_GETFIELD: {
INCPC(3);
NEXT_INSTRUCTION;
}
case OPCODE_PUTFIELD: {
INCPC(3);
NEXT_INSTRUCTION;
}
case OPCODE_INVOKEINTERFACE: {
INCPC(5);
NEXT_INSTRUCTION;
}
case OPCODE_NEW: {
INCPC(3);
NEXT_INSTRUCTION;
}
case OPCODE_ANEWARRAY: {
INCPC(3);
NEXT_INSTRUCTION;
}
case OPCODE_ARRAYLENGTH: {
INCPC(1);
NEXT_INSTRUCTION;
}
case OPCODE_ATHROW: {
NEXT_INSTRUCTION_WITH_POLL_CHECK;
}
case OPCODE_CHECKCAST: {
INCPC(3);
NEXT_INSTRUCTION;
}
case OPCODE_INSTANCEOF: {
INCPC(3);
NEXT_INSTRUCTION;
}
case OPCODE_MONITORENTER: {
INCPC(1);
NEXT_INSTRUCTION;
}
case OPCODE_MONITOREXIT: {
INCPC(1);
NEXT_INSTRUCTION;
}
case OPCODE_WIDE: {
}
case OPCODE_MULTIANEWARRAY: {
INCPC(4);
NEXT_INSTRUCTION;
}
case OPCODE_IFNULL: {
INCPC(3);
NEXT_INSTRUCTION_WITH_POLL_CHECK;
}
case OPCODE_IFNONNULL: {
INCPC(3);
NEXT_INSTRUCTION_WITH_POLL_CHECK;
}
case OPCODE_GOTO_W: {
INCPC(1);
NEXT_INSTRUCTION_WITH_POLL_CHECK;
}
case OPCODE_JSR_W: {
INCPC(1);
NEXT_INSTRUCTION_WITH_POLL_CHECK;
}
case OPCODE_GETFIELD_QUICK: {
INCPC(3);
NEXT_INSTRUCTION;
}
case OPCODE_PUTFIELD_QUICK: {
INCPC(3);
NEXT_INSTRUCTION;
}
case OPCODE_GETFIELD2_QUICK: {
INCPC(3);
NEXT_INSTRUCTION;
}
case OPCODE_PUTFIELD2_QUICK: {
INCPC(3);
NEXT_INSTRUCTION;
}
case OPCODE_INVOKEVIRTUAL_QUICK: {
{
}
{
}
INCPC(3);
NEXT_INSTRUCTION_WITH_POLL_CHECK;
}
case OPCODE_INVOKENONVIRTUAL_QUICK: {
INCPC(3);
NEXT_INSTRUCTION_WITH_POLL_CHECK;
}
case OPCODE_DEBUG_PRINT: {
INCPC(1);
NEXT_INSTRUCTION;
}
case OPCODE_PRINT_STRING: {
INCPC(1);
NEXT_INSTRUCTION;
}
case OPCODE_WIDE_ILOAD: {
INCPC(3);
NEXT_INSTRUCTION;
}
case OPCODE_WIDE_LLOAD: {
INCPC(3);
NEXT_INSTRUCTION;
}
case OPCODE_WIDE_FLOAD: {
INCPC(3);
NEXT_INSTRUCTION;
}
case OPCODE_WIDE_DLOAD: {
INCPC(3);
NEXT_INSTRUCTION;
}
case OPCODE_WIDE_ALOAD: {
INCPC(3);
NEXT_INSTRUCTION;
}
case OPCODE_WIDE_ISTORE: {
INCPC(3);
NEXT_INSTRUCTION;
}
case OPCODE_WIDE_LSTORE: {
INCPC(3);
NEXT_INSTRUCTION;
}
case OPCODE_WIDE_FSTORE: {
INCPC(3);
NEXT_INSTRUCTION;
}
case OPCODE_WIDE_DSTORE: {
INCPC(3);
NEXT_INSTRUCTION;
}
case OPCODE_WIDE_ASTORE: {
INCPC(3);
NEXT_INSTRUCTION;
}
case OPCODE_WIDE_IINC: {
INCPC(5);
NEXT_INSTRUCTION;
}
case OPCODE_WIDE_RET: {
NEXT_INSTRUCTION_WITH_POLL_CHECK;
}
